prefix/__init__.py
prefix/_/__init__.py
prefix/_/command.py
prefix-0.0.1.dist-info/LICENSE
prefix-0.0.1.dist-info/METADATA
prefix-0.0.1.dist-info/WHEEL
prefix-0.0.1.dist-info/top_level.txt
prefix-0.0.1.dist-info/zip-safe
prefix-0.0.1.dist-info/RECORD
